CHANGELOG.txt
LICENSE.txt
MANIFEST.in
README.txt
setup.py
st7036.py
st7036.egg-info/PKG-INFO
st7036.egg-info/SOURCES.txt
st7036.egg-info/dependency_links.txt
st7036.egg-info/requires.txt
st7036.egg-info/top_level.txt