Metadata-Version: 1.1
Name: st7036
Version: 1.4.3
Summary: Raspberry Pi ST7036 SPI Driver
Home-page: http://www.pimoroni.com
Author: Jonathan Williamson
Author-email: jon@pimoroni.com
License: MIT
Keywords: Raspberry Pi ST7036 SPI
Platform: UNKNOWN
Classifier: Development Status :: 5 - Production/Stable
Classifier: Operating System :: POSIX :: Linux
Classifier: License :: OSI Approved :: MIT License
Classifier: Intended Audience :: Developers
Classifier: Programming Language :: Python :: 2.6
Classifier: Programming Language :: Python :: 2.7
Classifier: Programming Language :: Python :: 3
Classifier: Topic :: Software Development
Classifier: Topic :: System :: Hardware
